{
    "info": {
        "Godina": "2011",
        "Ime i prezime funkcionera ": "AMER HALILOVI\u0106",
        "Naziv izvje\u0161taja": "Godi\u0161nji izvje\u0161taj za vrijeme obavljanja funkcije",
        "Vrsta funkcionera": "Poslanici Crne Gore"
    },
    "link": "http://www.konfliktinteresa.me/new/evid_funkc/funkcioneri/EvidFunPrijavePrikaz.php?ID=OD4-MTU8MyY8PT43OA,,&Godina=2011&Rbr=1",
    "tables": [
        {
            "Adresa": "",
            "Druga javna funkcija ": " / - Postavljena od: / - visina mjesecne zarade /",
            "Godi\u0161nji prihod od poljoprivrede i dr. djelatnosti ": " LIVADA- u iznosu 200 \u20ac eura; \u0160UMA- u iznosu 800 eura",
            "Javna funkcija ": " POSLANIK - Postavljena od: SKUP\u0160TINA CG - visina mjesecne zarade 1300 \u20ac",
            "Krediti, dugovi i potra\u017eivanja ": " KREDIT - CKB- iznos duga: 27000 \u20ac - iznos potrazivanja :/ - rok otplate/naplate: 20 GODINA",
            "Mjese\u010dna nadoknada ": "",
            "Mjese\u010dna plata ": "",
            "Nepokretna imovina ": " KU\u0106A-RO\u017dAJE-140 M2-vlasnistvo(1/1); LIVADA-IBARAC-1 HA-vlasnistvo(1/1); /-/-/-vlasnistvo(/); /-/-/-vlasnistvo(/)",
            "Obavljanje drugih djelatnosti ": " FOND ZA MANJINE-\u010cLAN UO iznos: 165 \u20ac eura; DOM ZDRAVLJA RO\u017dAJE-UGOVOR O DJELU iznos: 150 \u20ac MJESE\u010cNO eura",
            "Ostala pokretna imovina ": "",
            "Ostali prihodi ": "",
            "Pokretna imovina ": " PMV-MERCEDES C 200-1993",
            "Stalni radni odnos ": "Institucija: SKUP\u0160TINA CG - adresa: PODGORICA visina mjesecne zarade: 1300 \u20ac",
            "Vlasni\u0161tvo u privrednim dru\u0161tvima ": "",
            "\u010clan organa privrednog dru\u0161tva ": ""
        },
        {
            "Ime bra\u010dnog/vanbra\u010dnog druga ": "MURATKA HALILOVI\u0106",
            "Krediti, dugovi i potra\u017eivanja ": "",
            "Mjese\u010dna plata ": "",
            "Nepokretna imovina ": "",
            "Obavljanje drugih djelatnosti ": "",
            "Ostala pokretna imovina ": "",
            "Ostali prihodi ": "",
            "Pokretna imovina ": "",
            "Prihodi od poljop,slobod i drugih djeltanosti ": "",
            "Stalni radni odnos ": "",
            "Vlasni\u0161tvo u privrednim dru\u0161tvima ": ""
        },
        {
            "Ime i prezime Djeteta ": "AMIL HALILOVI\u0106",
            "Mjese\u00e8na plata ": "",
            "Nepokretna imovina ": "",
            "Ostala pokretna imovina ": "",
            "Ostali prihodi ": "",
            "Pokretna imovina ": "",
            "Prihodi od poljop,slobod i drugih djeltanosti ": "",
            "Vlasni\u0161tvo u privrednim dru\u0161tvima ": ""
        },
        {
            "Ime i prezime Djeteta ": "ALMEDINA HALILOVI\u0106",
            "Mjese\u00e8na plata ": "",
            "Nepokretna imovina ": "",
            "Ostala pokretna imovina ": "",
            "Ostali prihodi ": "",
            "Pokretna imovina ": "",
            "Prihodi od poljop,slobod i drugih djeltanosti ": "",
            "Vlasni\u0161tvo u privrednim dru\u0161tvima ": ""
        },
        {
            "Ime i prezime Djeteta ": "ZIJAD HALILOVI\u0106",
            "Mjese\u00e8na plata ": "",
            "Nepokretna imovina ": "",
            "Ostala pokretna imovina ": "",
            "Ostali prihodi ": "",
            "Pokretna imovina ": "",
            "Prihodi od poljop,slobod i drugih djeltanosti ": "",
            "Vlasni\u0161tvo u privrednim dru\u0161tvima ": ""
        },
        {
            "Ime i prezime Djeteta ": "SEMINA HALILOVI\u0106",
            "Mjese\u00e8na plata ": "",
            "Nepokretna imovina ": "",
            "Ostala pokretna imovina ": "",
            "Ostali prihodi ": "",
            "Pokretna imovina ": "",
            "Prihodi od poljop,slobod i drugih djeltanosti ": "",
            "Vlasni\u0161tvo u privrednim dru\u0161tvima ": ""
        }
    ]
}
