{
    "info": {
        "Godina": "2009",
        "Ime i prezime funkcionera ": "ZORICA KOVA\u010cEVI\u0106",
        "Naziv izvje\u0161taja": "Godi\u0161nji izvje\u0161taj za vrijeme obavljanja funkcije",
        "Vrsta funkcionera": "Vladini funkcioneri"
    },
    "link": "http://www.konfliktinteresa.me/new/evid_funkc/funkcioneri/EvidFunPrijavePrikaz.php?ID=Oj4-MzU8PSY6Nz40PA,,&Godina=2009&Rbr=1",
    "tables": [
        {
            "Adresa": "DANILOVGRAD,KOSI\u0106",
            "Druga javna funkcija ": "DIREKTOR DOMA ZDRAVLJA DANILOVGRAD (2005-2009)",
            "Godi\u0161nji prihod od poljoprivrede i dr. djelatnosti ": "",
            "Javna funkcija ": "ODBORNIK SO DANILOVGRAD",
            "Krediti, dugovi i potra\u017eivanja ": "",
            "Mjese\u010dna nadoknada ": "",
            "Mjese\u010dna plata ": "680 \u20ac",
            "Nepokretna imovina ": "PODGORICA - STAN - 51 M2",
            "Obavljanje drugih djelatnosti ": "",
            "Ostala pokretna imovina ": "UMJETNI\u010cKE SLIKE  MVP - HLT",
            "Ostali prihodi ": "NAKNADA ZA OBAVLJANJE ODBORNI\u010cKE FUNKCIJE - 1200 \u20ac GODI\u0160NJE",
            "Pokretna imovina ": "",
            "Stalni radni odnos ": "",
            "Vlasni\u0161tvo u privrednim dru\u0161tvima ": "",
            "\u010clan organa privrednog dru\u0161tva ": "\u010cLAN ODBORA DIREKTORA JU OP\u0160TA BOLNICA - BAR"
        },
        {
            "Ime bra\u010dnog/vanbra\u010dnog druga ": "",
            "Krediti, dugovi i potra\u017eivanja ": "",
            "Mjese\u010dna plata ": "",
            "Nepokretna imovina ": "",
            "Obavljanje drugih djelatnosti ": "",
            "Ostala pokretna imovina ": "",
            "Ostali prihodi ": "",
            "Pokretna imovina ": "",
            "Prihodi od poljop,slobod i drugih djeltanosti ": "",
            "Stalni radni odnos ": "",
            "Vlasni\u0161tvo u privrednim dru\u0161tvima ": ""
        },
        {
            "Ime i prezime Djeteta ": "",
            "Mjese\u00e8na plata ": "",
            "Nepokretna imovina ": "",
            "Ostala pokretna imovina ": "",
            "Ostali prihodi ": "",
            "Pokretna imovina ": "",
            "Prihodi od poljop,slobod i drugih djeltanosti ": "",
            "Vlasni\u0161tvo u privrednim dru\u0161tvima ": ""
        }
    ]
}
