{"info": {"Ime i prezime funkcionera ": "ALMER H. KALA\u010c", "Vrsta funkcionera": "Op\u0161tinski funkcioneri", "Godina": "2010", "Naziv izvje\u0161taja": "Na dan stupanja na funkciju"}, "tables": [{"Stalni radni odnos ": "Institucija: ACOS DOO - adresa: RO\u017dAJE visina mjesecne zarade: 400", "Ostala pokretna imovina ": " U\u0160TE\u0110EVINA-vrijednost: 8000 eura", "Mjese\u010dna plata ": "", "\u010clan organa privrednog dru\u0161tva ": "", "Ostali prihodi ": "", "Javna funkcija ": " ODBORNIK - Postavljena od: SO RO\u017dAJE - visina mjesecne zarade 110", "Godi\u0161nji prihod od poljoprivrede i dr. djelatnosti ": " VO\u0106E I POVR\u0106E- u iznosu nema nadoknade ili je nepoznata", "Adresa": "", "Mjese\u010dna nadoknada ": "", "Druga javna funkcija ": "", "Pokretna imovina ": " PMV-OPEL FRONTERA-1993", "Obavljanje drugih djelatnosti ": " STRU\u010cNI KONSULTANT-KONSULTANT iznos: 50 - 100 \u20ac eura", "Vlasni\u0161tvo u privrednim dru\u0161tvima ": "", "Nepokretna imovina ": " KU\u0106A-KALA\u010cE-190-vlasnistvo(/)", "Krediti, dugovi i potra\u017eivanja ": " KREDIT- iznos duga: 15000 - iznos potrazivanja :/ - rok otplate/naplate: 10 GODINA"}, {"Ostala pokretna imovina ": "", "Mjese\u010dna plata ": "", "Ime bra\u010dnog/vanbra\u010dnog druga ": "ALMIRA KALA\u010c", "Ostali prihodi ": "", "Stalni radni odnos ": "", "Nepokretna imovina ": "", "Pokretna imovina ": "", "Prihodi od poljop,slobod i drugih djeltanosti ": "", "Vlasni\u0161tvo u privrednim dru\u0161tvima ": "", "Obavljanje drugih djelatnosti ": "", "Krediti, dugovi i potra\u017eivanja ": ""}, {"Ostala pokretna imovina ": "", "Ostali prihodi ": "", "Pokretna imovina ": "", "Ime i prezime Djeteta ": "BERINA KALA\u010c", "Mjese\u00e8na plata ": "", "Prihodi od poljop,slobod i drugih djeltanosti ": "", "Nepokretna imovina ": "", "Vlasni\u0161tvo u privrednim dru\u0161tvima ": ""}, {"Ostala pokretna imovina ": "", "Ostali prihodi ": "", "Pokretna imovina ": "", "Ime i prezime Djeteta ": "AHMED KALA\u010c", "Mjese\u00e8na plata ": "", "Prihodi od poljop,slobod i drugih djeltanosti ": "", "Nepokretna imovina ": "", "Vlasni\u0161tvo u privrednim dru\u0161tvima ": ""}], "link": "http://www.konfliktinteresa.me/new/evid_funkc/funkcioneri/EvidFunPrijavePrikaz.php?ID=Ojg-NDU-PiY8PT41OA,,&Godina=2010&Rbr=1"}