{"info": {"Ime i prezime funkcionera ": "RAFET HUSOVI\u0106", "Vrsta funkcionera": "Vlada", "Godina": "2009", "Naziv izvje\u0161taja": "Na dan stupanja na funkciju"}, "tables": [{"Stalni radni odnos ": "", "Ostala pokretna imovina ": "", "Mjese\u010dna plata ": "950 \u20ac", "\u010clan organa privrednog dru\u0161tva ": "", "Ostali prihodi ": "", "Javna funkcija ": "MINISTAR BEZ PORTFELJA", "Godi\u0161nji prihod od poljoprivrede i dr. djelatnosti ": "", "Adresa": "RO\u017dAJE", "Mjese\u010dna nadoknada ": "", "Druga javna funkcija ": "", "Pokretna imovina ": "PMV - MERCEDES BENZ 210 - 1997. GOD", "Obavljanje drugih djelatnosti ": "", "Vlasni\u0161tvo u privrednim dru\u0161tvima ": "MVP - EPCG; MAOS; EURF; MONF; TREND; TECG; PLAP; KAPCG", "Nepokretna imovina ": "RO\u017dAJE - PLAC - ZEMLJI\u0160TE - 539 M2;  RO\u017dAJE - KU\u0106A - 180 M2 + 40 M2 GARA\u017dE - HIPOTEKA KOD ATLAS MONT BANKE;  ULCINJ - PLAC - ZEMLJI\u0160TE - 1078 M2 - HIPOTEKA KOD NLB BANKE", "Krediti, dugovi i potra\u017eivanja ": ""}, {"Ostala pokretna imovina ": "", "Mjese\u010dna plata ": "440 \u20ac", "Ime bra\u010dnog/vanbra\u010dnog druga ": "JASMINA HUSOVI\u0106", "Ostali prihodi ": "", "Stalni radni odnos ": "", "Nepokretna imovina ": "", "Pokretna imovina ": "", "Prihodi od poljop,slobod i drugih djeltanosti ": "", "Vlasni\u0161tvo u privrednim dru\u0161tvima ": "MVP - TREND", "Obavljanje drugih djelatnosti ": "", "Krediti, dugovi i potra\u017eivanja ": ""}, {"Ostala pokretna imovina ": "", "Ostali prihodi ": "", "Pokretna imovina ": "", "Ime i prezime Djeteta ": "SANDRA HUSOVI\u0106", "Mjese\u00e8na plata ": "", "Prihodi od poljop,slobod i drugih djeltanosti ": "", "Nepokretna imovina ": "", "Vlasni\u0161tvo u privrednim dru\u0161tvima ": ""}, {"Ostala pokretna imovina ": "", "Ostali prihodi ": "", "Pokretna imovina ": "", "Ime i prezime Djeteta ": "ENES HUSOVI\u0106", "Mjese\u00e8na plata ": "", "Prihodi od poljop,slobod i drugih djeltanosti ": "", "Nepokretna imovina ": "", "Vlasni\u0161tvo u privrednim dru\u0161tvima ": ""}], "link": "http://www.konfliktinteresa.me/new/evid_funkc/funkcioneri/EvidFunPrijavePrikaz.php?ID=Oz0-MjU_PyY8PT40PA,,&Godina=2009&Rbr=1"}