{
    "info": {
        "Godina": "2013",
        "Ime i prezime funkcionera ": "NEVEN GO\u0160OVI\u0106",
        "Naziv izvje\u0161taja": "Godi\u0161nji izvje\u0161taj za vrijeme obavljanja funkcije",
        "Vrsta funkcionera": "Poslanici Crne Gore"
    },
    "link": "http://www.konfliktinteresa.me/new/evid_funkc/funkcioneri/EvidFunPrijavePrikaz.php?ID=Oz0_NzU8OCY6Pz43PQ,,&Godina=2013&Rbr=1",
    "tables": [
        {
            "Adresa": "",
            "Druga javna funkcija ": " \u010cLAN SUDSKOG SAVJETA - Postavljena od: SUDSKI SAVJET - visina mjesecne zarade 500 \u20ac za mjesece: januar, februar,, mart, jul, avgust, septembar, oktobar, novembar i decembar; 316 \u20ac za april; 250 \u20ac za jun- ukupno za 2012 godinu= 5.066 \u20ac; PREDSJEDNIK KOMISIJE ZA ETI\u010cKI KODEKS SUDIJA - Postavljena od: / - visina mjesecne zarade 240 \u20ac ( UKUPNO UPLA\u0106ENI IZNOS ZA 2012 G. = 2.299 \u20ac); / - Postavljena od: / - visina mjesecne zarade /",
            "Godi\u0161nji prihod od poljoprivrede i dr. djelatnosti ": "",
            "Javna funkcija ": " POSLANIK - Postavljena od: SKUP\u0160TINA CG - visina mjesecne zarade 1516.95 \u20ac",
            "Krediti, dugovi i potra\u017eivanja ": "",
            "Mjese\u010dna nadoknada ": "",
            "Mjese\u010dna plata ": "",
            "Nepokretna imovina ": " STAN-PODGORICA-37 M2-vlasnistvo(100%); STARA PORODI\u010cNA KU\u0106A I IMANJE OSTA. POSTUPAK NIJE VODJEN VI\u0160E NASLJ.-PODGORICA - KU\u010cI-UPIS PREMA KATASTRU BEZ IZVR\u0160ENOG PREMJERA-vlasnistvo(/)",
            "Obavljanje drugih djelatnosti ": "",
            "Ostala pokretna imovina ": "",
            "Ostali prihodi ": "",
            "Pokretna imovina ": " PMV-GOLF-1992",
            "Stalni radni odnos ": "Institucija: SKUP\u0160TINA CG - adresa: PODGORICA visina mjesecne zarade: 1516.95 \u20ac (+ 225 \u20ac NAKNADA ZA RAD U SKUP\u0160TINSKIM ODBORIMA)",
            "Vlasni\u0161tvo u privrednim dru\u0161tvima ": "",
            "\u010clan organa privrednog dru\u0161tva ": ""
        },
        {
            "Ime bra\u010dnog/vanbra\u010dnog druga ": "",
            "Krediti, dugovi i potra\u017eivanja ": "",
            "Mjese\u010dna plata ": "",
            "Nepokretna imovina ": "",
            "Obavljanje drugih djelatnosti ": "",
            "Ostala pokretna imovina ": "",
            "Ostali prihodi ": "",
            "Pokretna imovina ": "",
            "Prihodi od poljop,slobod i drugih djeltanosti ": "",
            "Stalni radni odnos ": "",
            "Vlasni\u0161tvo u privrednim dru\u0161tvima ": ""
        },
        {
            "Ime i prezime Djeteta ": "",
            "Mjese\u00e8na plata ": "",
            "Nepokretna imovina ": "",
            "Ostala pokretna imovina ": "",
            "Ostali prihodi ": "",
            "Pokretna imovina ": "",
            "Prihodi od poljop,slobod i drugih djeltanosti ": "",
            "Vlasni\u0161tvo u privrednim dru\u0161tvima ": ""
        }
    ]
}
